vbll/__init__.py
vbll/jax/__init__.py
vbll/jax/layers/__init__.py
vbll/jax/layers/regression.py
vbll/jax/utils/distributions.py
vbll/layers/__init__.py
vbll/layers/classification.py
vbll/layers/regression.py
vbll/utils/distributions.py
vbll-0.4.9.dist-info/METADATA
vbll-0.4.9.dist-info/WHEEL
vbll-0.4.9.dist-info/RECORD
