Metadata-Version: 2.1
Name: vbll
Version: 0.4.9
Summary: 
Author: John Willes
Author-email: johnwilles@gmail.com
Requires-Python: >=3.9,<4.0
Classifier: Programming Language :: Python :: 3
Classifier: Programming Language :: Python :: 3.9
Classifier: Programming Language :: Python :: 3.10
Classifier: Programming Language :: Python :: 3.11
Classifier: Programming Language :: Python :: 3.12
Requires-Dist: numpy (>=1.21.0)
Requires-Dist: torch (>=1.6.0)
